django_manifeststaticfiles_enhanced/__init__.py
django_manifeststaticfiles_enhanced/jslex.py
django_manifeststaticfiles_enhanced/storage.py
django_manifeststaticfiles_enhanced/management/__init__.py
django_manifeststaticfiles_enhanced/management/commands/__init__.py
django_manifeststaticfiles_enhanced/management/commands/collectstatic.py
django_manifeststaticfiles_enhanced-0.7.4.dist-info/licenses/LICENSE
django_manifeststaticfiles_enhanced-0.7.4.dist-info/METADATA
django_manifeststaticfiles_enhanced-0.7.4.dist-info/WHEEL
django_manifeststaticfiles_enhanced-0.7.4.dist-info/top_level.txt
django_manifeststaticfiles_enhanced-0.7.4.dist-info/RECORD
