Metadata-Version: 2.4
Name: django-manifeststaticfiles-enhanced
Version: 0.7.4
Summary: Enhanced ManifestStaticFilesStorage for Django
Author: Django ManifestStaticFiles Enhanced Contributors
License-Expression: BSD-3-Clause
Project-URL: Homepage, https://github.com/blighj/django-manifeststaticfiles-enhanced
Project-URL: Repository, https://github.com/blighj/django-manifeststaticfiles-enhanced
Project-URL: Issues, https://github.com/blighj/django-manifeststaticfiles-enhanced/issues
Keywords: django,staticfiles,manifest,collectstatic
Classifier: Development Status :: 4 - Beta
Classifier: Environment :: Web Environment
Classifier: Framework :: Django
Classifier: Framework :: Django :: 4.2
Classifier: Framework :: Django :: 5.0
Classifier: Framework :: Django :: 5.1
Classifier: Framework :: Django :: 5.2
Classifier: Framework :: Django :: 6.0
Classifier: Intended Audience :: Developers
Classifier: Operating System :: OS Independent
Classifier: Programming Language :: Python
Classifier: Programming Language :: Python :: 3
Classifier: Programming Language :: Python :: 3.9
Classifier: Programming Language :: Python :: 3.10
Classifier: Programming Language :: Python :: 3.11
Classifier: Programming Language :: Python :: 3.12
Classifier: Programming Language :: Python :: 3.13
Classifier: Topic :: Internet :: WWW/HTTP
Classifier: Topic :: Internet :: WWW/HTTP :: Dynamic Content
Classifier: Topic :: Software Development :: Libraries :: Python Modules
Requires-Python: >=3.9
License-File: LICENSE
Requires-Dist: Django>=4.2
Provides-Extra: dev
Requires-Dist: black>=22.0; extra == "dev"
Requires-Dist: isort>=5.0; extra == "dev"
Requires-Dist: flake8>=4.0; extra == "dev"
Dynamic: license-file
